solrbenchmark/__init__.py
solrbenchmark/docs.py
solrbenchmark/localtypes.py
solrbenchmark/py.typed
solrbenchmark/runner.py
solrbenchmark/schema.py
solrbenchmark/terms.py
solrbenchmark-0.1.0.dist-info/LICENSE
solrbenchmark-0.1.0.dist-info/METADATA
solrbenchmark-0.1.0.dist-info/WHEEL
solrbenchmark-0.1.0.dist-info/top_level.txt
solrbenchmark-0.1.0.dist-info/RECORD
