Metadata-Version: 2.1
Name: solrbenchmark
Version: 0.1.0
Summary: Python package for benchmarking Solr instances: generating and loading fake but realistic data, running tests, and logging results.
Author-email: Jason Thomale <jason.thomale@unt.edu>
Keywords: Solr,testing,benchmarking,data
Classifier: Development Status :: 3 - Alpha
Classifier: Intended Audience :: Developers
Classifier: License :: OSI Approved :: BSD License
Classifier: Programming Language :: Python
Classifier: Programming Language :: Python :: 3
Classifier: Programming Language :: Python :: 3 :: Only
Classifier: Programming Language :: Python :: 3.7
Classifier: Programming Language :: Python :: 3.8
Classifier: Programming Language :: Python :: 3.9
Classifier: Programming Language :: Python :: 3.10
Classifier: Programming Language :: Python :: 3.11
Classifier: Topic :: Software Development
Classifier: Topic :: Software Development :: Testing
Requires-Python: >=3.7
License-File: LICENSE
Requires-Dist: fauxdoc (>=1.0.0)
Requires-Dist: ujson (>=2.0.0) ; python_version <= "3.8"
Requires-Dist: importlib-metadata (>=2.0.0) ; python_version == "3.7"
Requires-Dist: typing-extensions (>=3.6.5) ; python_version == "3.7"
Requires-Dist: ujson (>=4.0.0) ; python_version == "3.9"
Requires-Dist: ujson (>=4.2.0) ; python_version >= "3.10"
Provides-Extra: dev
Requires-Dist: pysolr (>=3.9.0) ; extra == 'dev'
Requires-Dist: pytest (>=3.0.0) ; (python_version < "3.10") and extra == 'dev'
Requires-Dist: python-dotenv (>=0.10.3) ; (python_version == "3.7") and extra == 'dev'
Requires-Dist: python-dotenv (>=0.11.0) ; (python_version == "3.8") and extra == 'dev'
Requires-Dist: python-dotenv (>=0.15.0) ; (python_version == "3.9") and extra == 'dev'
Requires-Dist: pytest (>=6.2.4) ; (python_version >= "3.10") and extra == 'dev'
Requires-Dist: python-dotenv (>=0.19.1) ; (python_version >= "3.10") and extra == 'dev'
